gemspa/__init__.py
gemspa/advanced_group_analysis.py
gemspa/analyze_steps_and_tracks.py
gemspa/cli.py
gemspa/compare_conditions.py
gemspa/ensemble_analysis.py
gemspa/msd_diffusion.py
gemspa/rainbow_tracks.py
gemspa/step_size_analysis.py
gemspa/trackmate_prep.py
gemspa/trajectory_analysis.py
gemspa/utils/__init__.py
gemspa/utils/data_io.py
gemspa/utils/plotting.py
GEMspa_CLI-2.0.0.dist-info/LICENSE
GEMspa_CLI-2.0.0.dist-info/METADATA
GEMspa_CLI-2.0.0.dist-info/WHEEL
GEMspa_CLI-2.0.0.dist-info/entry_points.txt
GEMspa_CLI-2.0.0.dist-info/top_level.txt
GEMspa_CLI-2.0.0.dist-info/RECORD
