Metadata-Version: 2.1
Name: GEMspa-CLI
Version: 2.0.0
Summary: GEMspa: Advanced single-particle tracking analysis pipeline with MSD, diffusion analysis, and visualization tools
Author-email: "Andrew Bazley, Sarah Keegan" <Andrew.bazley@nyulangone.org>
License: MIT
Keywords: single-particle tracking,MSD,diffusion,trackmate,microscopy,analysis
Classifier: Development Status :: 4 - Beta
Classifier: Intended Audience :: Science/Research
Classifier: License :: OSI Approved :: MIT License
Classifier: Operating System :: OS Independent
Classifier: Programming Language :: Python :: 3
Classifier: Programming Language :: Python :: 3.7
Classifier: Programming Language :: Python :: 3.8
Classifier: Programming Language :: Python :: 3.9
Classifier: Programming Language :: Python :: 3.10
Classifier: Programming Language :: Python :: 3.11
Classifier: Topic :: Scientific/Engineering :: Bio-Informatics
Classifier: Topic :: Scientific/Engineering :: Physics
Requires-Python: >=3.7
License-File: LICENSE
Requires-Dist: numpy <2.0.0,>=1.21.0
Requires-Dist: pandas <3.0.0,>=1.3.0
Requires-Dist: scipy <2.0.0,>=1.7.0
Requires-Dist: matplotlib <4.0.0,>=3.4.0
Requires-Dist: seaborn <1.3.0,>=0.11.0
Requires-Dist: scikit-image <0.22.0,>=0.19.0
Requires-Dist: tifffile <2025.0.0,>=2020.12.8
Requires-Dist: nd2reader <4.0.0,>=3.0.0
Requires-Dist: joblib <2.0.0,>=1.2.0
Requires-Dist: numba <0.61.0,>=0.55.0
